[{"name":"sprite1","x":184,"y":2,"width":27,"height":29},{"name":"sprite2","x":150,"y":3,"width":27,"height":27},{"name":"sprite3","x":116,"y":5,"width":27,"height":27},{"name":"sprite4","x":239,"y":7,"width":21,"height":26},{"name":"sprite5","x":338,"y":7,"width":20,"height":27},{"name":"sprite6","x":267,"y":8,"width":21,"height":25},{"name":"sprite7","x":373,"y":8,"width":21,"height":24},{"name":"sprite8","x":296,"y":9,"width":22,"height":26},{"name":"sprite9","x":406,"y":9,"width":20,"height":25},{"name":"sprite10","x":75,"y":10,"width":21,"height":23},{"name":"sprite11","x":7,"y":13,"width":21,"height":16},{"name":"sprite12","x":43,"y":13,"width":19,"height":21},{"name":"sprite13","x":410,"y":40,"width":26,"height":22},{"name":"sprite14","x":267,"y":43,"width":26,"height":25},{"name":"sprite15","x":339,"y":43,"width":26,"height":22},{"name":"sprite16","x":372,"y":43,"width":26,"height":23},{"name":"sprite17","x":150,"y":44,"width":31,"height":27},{"name":"sprite18","x":188,"y":44,"width":30,"height":27},{"name":"sprite19","x":232,"y":44,"width":27,"height":25},{"name":"sprite20","x":111,"y":45,"width":30,"height":26},{"name":"sprite21","x":298,"y":45,"width":26,"height":23},{"name":"sprite22","x":40,"y":48,"width":22,"height":21},{"name":"sprite23","x":75,"y":48,"width":23,"height":21},{"name":"sprite24","x":4,"y":50,"width":25,"height":18},{"name":"sprite25","x":294,"y":54,"width":1,"height":2},{"name":"sprite26","x":409,"y":72,"width":26,"height":22},{"name":"sprite27","x":338,"y":74,"width":26,"height":22},{"name":"sprite28","x":147,"y":75,"width":31,"height":27},{"name":"sprite29","x":266,"y":75,"width":25,"height":25},{"name":"sprite30","x":371,"y":75,"width":26,"height":23},{"name":"sprite31","x":110,"y":76,"width":30,"height":26},{"name":"sprite32","x":188,"y":76,"width":30,"height":27},{"name":"sprite33","x":231,"y":77,"width":27,"height":25},{"name":"sprite34","x":299,"y":77,"width":26,"height":23},{"name":"sprite35","x":41,"y":82,"width":22,"height":21},{"name":"sprite36","x":6,"y":83,"width":24,"height":18},{"name":"sprite37","x":75,"y":83,"width":23,"height":21},{"name":"sprite38","x":263,"y":85,"width":2,"height":3},{"name":"sprite39","x":264,"y":90,"width":1,"height":1},{"name":"sprite40","x":120,"y":112,"width":26,"height":32},{"name":"sprite41","x":181,"y":113,"width":26,"height":32},{"name":"sprite42","x":150,"y":114,"width":27,"height":32},{"name":"sprite43","x":239,"y":115,"width":19,"height":28},{"name":"sprite44","x":271,"y":116,"width":19,"height":25},{"name":"sprite45","x":376,"y":116,"width":20,"height":23},{"name":"sprite46","x":405,"y":116,"width":20,"height":24},{"name":"sprite47","x":301,"y":117,"width":19,"height":27},{"name":"sprite48","x":341,"y":117,"width":18,"height":24},{"name":"sprite49","x":8,"y":119,"width":21,"height":24},{"name":"sprite50","x":44,"y":121,"width":19,"height":20},{"name":"sprite51","x":78,"y":122,"width":19,"height":17},{"name":"sprite52","x":270,"y":152,"width":21,"height":28},{"name":"sprite53","x":301,"y":152,"width":21,"height":29},{"name":"sprite54","x":338,"y":152,"width":23,"height":23},{"name":"sprite55","x":406,"y":152,"width":23,"height":23},{"name":"sprite56","x":238,"y":153,"width":21,"height":29},{"name":"sprite57","x":375,"y":153,"width":23,"height":23},{"name":"sprite58","x":75,"y":154,"width":24,"height":29},{"name":"sprite59","x":6,"y":155,"width":24,"height":29},{"name":"sprite60","x":39,"y":155,"width":25,"height":27},{"name":"sprite61","x":125,"y":155,"width":18,"height":27},{"name":"sprite62","x":157,"y":155,"width":17,"height":26},{"name":"sprite63","x":189,"y":155,"width":17,"height":27},{"name":"sprite64","x":376,"y":185,"width":24,"height":25},{"name":"sprite65","x":153,"y":187,"width":24,"height":25},{"name":"sprite66","x":269,"y":187,"width":24,"height":27},{"name":"sprite67","x":409,"y":187,"width":24,"height":24},{"name":"sprite68","x":81,"y":188,"width":25,"height":26},{"name":"sprite69","x":232,"y":188,"width":23,"height":25},{"name":"sprite70","x":339,"y":188,"width":23,"height":24},{"name":"sprite71","x":39,"y":189,"width":26,"height":26},{"name":"sprite72","x":188,"y":190,"width":23,"height":24},{"name":"sprite73","x":303,"y":190,"width":24,"height":25},{"name":"sprite74","x":3,"y":191,"width":28,"height":25},{"name":"sprite75","x":115,"y":191,"width":23,"height":24},{"name":"sprite76","x":152,"y":217,"width":24,"height":25},{"name":"sprite77","x":188,"y":219,"width":23,"height":24},{"name":"sprite78","x":232,"y":219,"width":23,"height":25},{"name":"sprite79","x":269,"y":219,"width":24,"height":27},{"name":"sprite80","x":375,"y":219,"width":24,"height":25},{"name":"sprite81","x":408,"y":219,"width":24,"height":24},{"name":"sprite82","x":39,"y":220,"width":26,"height":26},{"name":"sprite83","x":82,"y":220,"width":25,"height":26},{"name":"sprite84","x":117,"y":220,"width":23,"height":24},{"name":"sprite85","x":301,"y":221,"width":24,"height":25},{"name":"sprite86","x":339,"y":221,"width":23,"height":24},{"name":"sprite87","x":3,"y":222,"width":28,"height":25},{"name":"sprite88","x":240,"y":252,"width":19,"height":29},{"name":"sprite89","x":300,"y":252,"width":19,"height":29},{"name":"sprite90","x":409,"y":252,"width":23,"height":25},{"name":"sprite91","x":161,"y":253,"width":17,"height":25},{"name":"sprite92","x":270,"y":253,"width":19,"height":27},{"name":"sprite93","x":338,"y":253,"width":23,"height":25},{"name":"sprite94","x":124,"y":254,"width":16,"height":29},{"name":"sprite95","x":188,"y":254,"width":16,"height":29},{"name":"sprite96","x":375,"y":254,"width":23,"height":24},{"name":"sprite97","x":76,"y":255,"width":24,"height":29},{"name":"sprite98","x":39,"y":257,"width":25,"height":27},{"name":"sprite99","x":4,"y":258,"width":24,"height":29}]